{
  "header": {
    "protoclVersion": {
      "protocolVersion": "0.0.2"
    }
  },
  "body": {
    "rx_obcTime": "1745143",
    "rx_recvCnt": "267",
    "rx_gpsDate": "170319",
    "rx_gpsTime": "121307",
    "rx_lat": 35.586924,
    "rx_long": 139.735776,
    "rx_alt": "-5",
    "rx_temp": "54.72",
    "rx_airP": "101914",
    "rx_bSize": "35",
    "tx_id": "23",
    "tx_cnt": "176",
    "payload": 1,
    "tx_gpsTime": "121257",
    "tx_lat": 35.585652,
    "tx_long": 139.736,
    "tx_alt": 0
  }
}