{
  "header": {
    "protoclVersion": {
      "protocolVersion": "0.0.1"
    }
  },
  "body": {
    "rx_obcTime": "430155",
    "rx_recvCnt": "26",
    "rx_gpsDate": "280219",
    "rx_gpsTime": "120220",
    "rx_lat": -8.695682000000488,
    "rx_long": 115.263528,
    "rx_alt": "1",
    "rx_temp": "31.87",
    "rx_airP": "100846",
    "rx_bSize": "36",
    "tx_id": "22",
    "tx_cnt": "160",
    "payload": 1,
    "tx_gpsTime": "120211",
    "tx_lat": -8.695604,
    "tx_long": 115.263496,
    "tx_alt": -0.00007800000048874267
  }
}