{
  "header": {
    "protoclVersion": {
      "protocolVersion": "0.0.2"
    }
  },
  "body": {
    "rx_obcTime": "2618216",
    "rx_recvCnt": "379",
    "rx_gpsDate": "110319",
    "rx_gpsTime": "80700",
    "rx_lat": 40.188456,
    "rx_long": 140.961776,
    "rx_alt": "11072",
    "rx_temp": "35.11",
    "rx_airP": "76939",
    "rx_bSize": "38",
    "tx_id": "23",
    "tx_cnt": "210",
    "payload": 1,
    "tx_gpsTime": "80650",
    "tx_lat": 40.166792,
    "tx_long": 140.955056,
    "tx_alt": 11080
  }
}