{
  "header": {
    "protoclVersion": {
      "protocolVersion": "0.0.2"
    }
  },
  "body": {
    "rx_obcTime": "2956777",
    "rx_recvCnt": "426",
    "rx_gpsDate": "100319",
    "rx_gpsTime": "65345",
    "rx_lat": 35.716196,
    "rx_long": 139.765552,
    "rx_alt": "33",
    "rx_temp": "31.97",
    "rx_airP": "101590",
    "rx_bSize": "35",
    "tx_id": "23",
    "tx_cnt": "190",
    "payload": 1,
    "tx_gpsTime": "65335",
    "tx_lat": 35.716256,
    "tx_long": 139.765648,
    "tx_alt": 25
  }
}