{
  "header": {
    "protoclVersion": {
      "protocolVersion": "0.0.1"
    }
  },
  "body": {
    "rx_obcTime": "23386585",
    "rx_recvCnt": "208",
    "rx_gpsDate": "50319",
    "rx_gpsTime": "210014",
    "rx_lat": -1.9537019999997938,
    "rx_long": 30.062168,
    "rx_alt": "1551",
    "rx_temp": "30.40",
    "rx_airP": "84610",
    "rx_bSize": "37",
    "tx_id": "23",
    "tx_cnt": "152",
    "payload": 1,
    "tx_gpsTime": "210005",
    "tx_lat": -1.953713,
    "tx_long": 30.061592,
    "tx_alt": 1667
  }
}