{
  "header": {
    "protoclVersion": {
      "protocolVersion": "0.0.2"
    }
  },
  "body": {
    "rx_obcTime": "6291052",
    "rx_recvCnt": "904",
    "rx_gpsDate": "150319",
    "rx_gpsTime": "55027",
    "rx_lat": 35.692068,
    "rx_long": 139.734816,
    "rx_alt": "12",
    "rx_temp": "33.01",
    "rx_airP": "101492",
    "rx_bSize": "35",
    "tx_id": "23",
    "tx_cnt": "192",
    "payload": 1,
    "tx_gpsTime": "55017",
    "tx_lat": 35.691472,
    "tx_long": 139.735088,
    "tx_alt": 16
  }
}