{
  "header": {
    "protoclVersion": {
      "protocolVersion": "0.0.2"
    }
  },
  "body": {
    "rx_obcTime": "624478",
    "rx_recvCnt": "92",
    "rx_gpsDate": "130319",
    "rx_gpsTime": "95505",
    "rx_lat": 35.78444,
    "rx_long": 140.03656,
    "rx_alt": "21",
    "rx_temp": "30.71",
    "rx_airP": "100587",
    "rx_bSize": "34",
    "tx_id": "23",
    "tx_cnt": "92",
    "payload": 1,
    "tx_gpsTime": "95456",
    "tx_lat": 35.784516,
    "tx_long": 140.040112,
    "tx_alt": 20
  }
}