{
  "header": {
    "protoclVersion": {
      "protocolVersion": "0.0.2"
    }
  },
  "body": {
    "rx_obcTime": "2178418",
    "rx_recvCnt": "287",
    "rx_gpsDate": "130319",
    "rx_gpsTime": "61548",
    "rx_lat": 42.785,
    "rx_long": 141.680048,
    "rx_alt": "19",
    "rx_temp": "33.65",
    "rx_airP": "99759",
    "rx_bSize": "34",
    "tx_id": "23",
    "tx_cnt": "34",
    "payload": 1,
    "tx_gpsTime": "61538",
    "tx_lat": 42.785436,
    "tx_long": 141.679856,
    "tx_alt": -4
  }
}