{
  "header": {
    "protoclVersion": {
      "protocolVersion": "0.0.1"
    }
  },
  "body": {
    "rx_obcTime": "1938190",
    "rx_recvCnt": "123",
    "rx_gpsDate": "280219",
    "rx_gpsTime": "33521",
    "rx_lat": 4286.261803,
    "rx_long": 115.233512,
    "rx_alt": "17",
    "rx_temp": "41.45",
    "rx_airP": "100889",
    "rx_bSize": "34",
    "tx_id": "21",
    "tx_cnt": "58",
    "payload": 1,
    "tx_gpsTime": "33511",
    "tx_lat": -8.705519,
    "tx_long": 115.23344,
    "tx_alt": 18
  }
}